HanTa/HanoverTagger.py
HanTa/__init__.py
HanTa/morphmodel_dutch.pgz
HanTa/morphmodel_en.pgz
HanTa/morphmodel_ger.pgz
HanTa-1.1.2.dist-info/LICENSE
HanTa-1.1.2.dist-info/METADATA
HanTa-1.1.2.dist-info/WHEEL
HanTa-1.1.2.dist-info/top_level.txt
HanTa-1.1.2.dist-info/RECORD
