Metadata-Version: 2.1
Name: HanTa
Version: 1.1.2
Summary: Hannover Tagger: Morphological Analysis and POS Tagging
Home-page: https://github.com/wartaal/HanTa
Author: Christian Wartena
Author-email: Christian.Wartena@hs-hannover.de
Classifier: Programming Language :: Python :: 3
Classifier: License :: OSI Approved :: GNU General Public License v3 (GPLv3)
Classifier: Operating System :: OS Independent
Classifier: Natural Language :: Dutch
Classifier: Natural Language :: English
Classifier: Natural Language :: German
Classifier: Topic :: Text Processing :: Linguistic
Classifier: Topic :: Software Development :: Libraries :: Python Modules
Classifier: Intended Audience :: Science/Research
Classifier: Intended Audience :: Developers
License-File: LICENSE
